servianwidgets/__init__.py
servianwidgets/scatterting.py
servianwidgets-1.0.3.dist-info/LICENSE.txt
servianwidgets-1.0.3.dist-info/METADATA
servianwidgets-1.0.3.dist-info/WHEEL
servianwidgets-1.0.3.dist-info/top_level.txt
servianwidgets-1.0.3.dist-info/RECORD
